setup.py
pocoui_lib/__init__.py
pocoui_lib.egg-info/PKG-INFO
pocoui_lib.egg-info/SOURCES.txt
pocoui_lib.egg-info/dependency_links.txt
pocoui_lib.egg-info/not-zip-safe
pocoui_lib.egg-info/requires.txt
pocoui_lib.egg-info/top_level.txt
pocoui_lib/android/__init__.py
pocoui_lib/android/kotoComponent.py
pocoui_lib/android/kotoList.py
pocoui_lib/android/kotoPage.py
pocoui_lib/android/kotoYyq.py
pocoui_lib/android/kotolixinli.py
pocoui_lib/crawler/__init__.py
pocoui_lib/crawler/branch.py
pocoui_lib/crawler/config.py
pocoui_lib/crawler/crawler.py
pocoui_lib/crawler/iosBranch.py
pocoui_lib/crawler/iosNode.py
pocoui_lib/crawler/node.py
pocoui_lib/crawler/path.py
pocoui_lib/ios/__init__.py
pocoui_lib/ios/kotoComponent.py
pocoui_lib/ios/kotoList.py
pocoui_lib/ios/kotoNav.py
pocoui_lib/ios/kotoPage.py
pocoui_lib/tools/__init__.py
pocoui_lib/tools/kotoPath.py
pocoui_lib/tools/kotoPhone.py