Metadata-Version: 1.0
Name: pocoui-lib
Version: 1.1.3
Summary: pocoui lib for souche-inc airtest project
Home-page: UNKNOWN
Author: mizhdi
Author-email: mizhdi@gmail.com
License: MIT
Platform: any
